biofile_kit/bin/fasta_tools.py
biofile_kit/bin/gff_tools.py
biofile_kit/bin/gt_kit.py
biofile_kit/bin/gtf_tools.py
biofile_kit/bin/vcf_tools.py
biofile_kit/fasta_utils/__init__.py
biofile_kit/fasta_utils/fa2tab.py
biofile_kit/fasta_utils/format_fasta.py
biofile_kit/fasta_utils/gap_location.py
biofile_kit/fasta_utils/generate_random_nucl.py
biofile_kit/fasta_utils/get_longest_seq_for_gene.py
biofile_kit/fasta_utils/get_reverse_complementary_seq.py
biofile_kit/fasta_utils/get_seq_len.py
biofile_kit/fasta_utils/hardmasked_to_softmasked.py
biofile_kit/fasta_utils/id_index_seq.py
biofile_kit/fasta_utils/motif_finder.py
biofile_kit/fasta_utils/ORF_finder.py
biofile_kit/fasta_utils/seq_rename.py
biofile_kit/fasta_utils/SSR_finder.py
biofile_kit/fasta_utils/telomere_finder.py
biofile_kit/gff_utils/__init__.py
biofile_kit/gff_utils/get_feature_density.py
biofile_kit/gff_utils/gff2bed.py
biofile_kit/gff_utils/gff2gtf.py
biofile_kit/gff_utils/gff_extract_seq.py
biofile_kit/gff_utils/gff_sort.py
biofile_kit/gff_utils/rename.py
biofile_kit/gff_utils/stats.py
biofile_kit/gt_utils/__init__.py
biofile_kit/gt_utils/genotype_consistency_analysis.py
biofile_kit/gt_utils/merge.py
biofile_kit/gt_utils/stat_gt.py
biofile_kit/gtf_utils/__init__.py
biofile_kit/gtf_utils/gtf2bed.py
biofile_kit/gtf_utils/gtf_extract_seq.py
biofile_kit/gtf_utils/gtf_sort.py
biofile_kit/vcf_utils/__init__.py
biofile_kit/vcf_utils/vcf2gt.py
biofile_kit-0.1.0.dist-info/entry_points.txt
biofile_kit-0.1.0.dist-info/LICENSE
biofile_kit-0.1.0.dist-info/METADATA
biofile_kit-0.1.0.dist-info/WHEEL
biofile_kit-0.1.0.dist-info/RECORD
