Metadata-Version: 2.1
Name: biofile-kit
Version: 0.1.0
Summary: Bioinformatics File Operations Toolkit.
Home-page: https://github.com/wenlinXu-njfu/BioFileKit
License: MIT
Author: Wenlin Xu
Author-email: wenlinxu.njfu@outlook.com
Requires-Python: >=3.8
Classifier: License :: OSI Approved :: MIT License
Classifier: Programming Language :: Python :: 3
Classifier: Programming Language :: Python :: 3.8
Classifier: Programming Language :: Python :: 3.9
Classifier: Programming Language :: Python :: 3.10
Classifier: Programming Language :: Python :: 3.11
Classifier: Programming Language :: Python :: 3.12
Classifier: Programming Language :: Python :: 3.13
Requires-Dist: pybioinformatic (>=1.2.5)
